shipbob/__init__.py
shipbob/client.py
shipbob/models/__init__.py
shipbob/models/base.py
shipbob/models/inventory.py
shipbob/models/orders.py
shipbob/models/products.py
shipbob/models/shipping.py
shipbob-0.2.0.dist-info/LICENSE
shipbob-0.2.0.dist-info/WHEEL
shipbob-0.2.0.dist-info/METADATA
shipbob-0.2.0.dist-info/RECORD
