Metadata-Version: 2.1
Name: shipbob
Version: 0.2.0
Summary: Client SDK for ShipBob API
Author: Raphael Lullis
Author-email: raphael@communityphone.org
Requires-Python: >=3.9,<4.0
Classifier: Programming Language :: Python :: 3
Classifier: Programming Language :: Python :: 3.9
Classifier: Programming Language :: Python :: 3.10
Classifier: Programming Language :: Python :: 3.11
Requires-Dist: pydantic (>=1.10.2,<2.0.0)
Requires-Dist: requests (>=2.28.1,<3.0.0)
